post_11/design.sv
// Code your design here
module mod_n_counter (input reset, clk, input [3:0] modulo, output reg [3:0] count );
    always @(posedge clk, posedge reset) begin
      if (reset) count <= 4'b0;
        else begin
            if (count < (modulo -1) ) begin
                 count <= count + 4'b0001;
            end
            else count <= 4'b0;
        end
    end
endmodule

post_11/testbench.sv
// Code your testbench here
// or browse Examples


//Using the default testbench from RTLHub

`timescale 1ns/1ps

module tb_top;
    // Testbench signals
  reg clk;
  reg reset;
  reg [3:0] modulo;
  wire [3:0] count;
    
    // Test counters
  integer test_count;
  integer pass_count;
  integer fail_count;

    // Instantiate the DUT (Device Under Test)
  mod_n_counter dut (
    .clk(clk),
    .reset(reset),
    .modulo(modulo),
    .count(count)
  );

    // Clock generation (10ns period = 100MHz)
  initial begin
    clk = 0;
    forever #5 clk = ~clk;
  end

    // Waveform dump
  initial begin
    $dumpfile("dump.vcd");
    $dumpvars(0, tb_top);
  end

    // Test sequence
  initial begin
        // Initialize counters
    test_count = 0;
    pass_count = 0;
    fail_count = 0;
        
    $display("Testing Variable Mod-N Counter");
    $display("Time | reset | modulo | count | Notes");
        
        // Initialize with reset
    reset = 1;
    modulo <= 4'd5;
    #12;
    $display("%4t |   %b   |   %2d   |  %2d   | Reset active", $time, reset, modulo, count);
        
    test_count = test_count + 1;
    if (count !== 4'd0) begin
      $display("ERROR: Count should be 0 during reset, got %d", count);
      fail_count = fail_count + 1;
    end else begin
      pass_count = pass_count + 1;
    end
    
        // Test Mod-5 Counter (0→1→2→3→4→0)
    reset = 0;
    #2;
    $display("\n--- Testing Mod-5 Counter ---");
    $display("%4t |   %b   |   %2d   |  %2d   | Reset released", $time, reset, modulo, count);
        
        // Count through one complete cycle
    repeat(5) begin
      @(posedge clk);
      #2;
      $display("%4t |   %b   |   %2d   |  %2d   | Counting", $time, reset, modulo, count);
    end
        
        // After 5 clocks, should be back at 0
    test_count = test_count + 1;
    if (count !== 4'd0) begin
      $display("ERROR: Mod-5 counter should wrap to 0, got %d", count);
      fail_count = fail_count + 1;
    end else begin
      pass_count = pass_count + 1;
    end
        
        // Test Mod-3 Counter
    modulo <= 4'd3;
    $display("\n--- Testing Mod-3 Counter ---");
        
        // Reset to start clean
    reset = 1;
    #2;
    reset = 0;
    #2;
    $display("%4t |   %b   |   %2d   |  %2d   | Switched to Mod-3", $time, reset, modulo, count);
    
        // Count through one complete cycle
    repeat(3) begin
      @(posedge clk);
      #2;
      $display("%4t |   %b   |   %2d   |  %2d   | Counting", $time, reset, modulo, count);
    end
        
        // After 3 clocks, should be back at 0
    test_count = test_count + 1;
    if (count !== 4'd0) begin
      $display("ERROR: Mod-3 counter should wrap to 0, got %d", count);
      fail_count = fail_count + 1;
    end else begin
      pass_count = pass_count + 1;
    end
        
    // Test Mod-10 Counter
    modulo <= 4'd10;
    $display("\n--- Testing Mod-10 Counter ---");
    reset = 1;
    #2;
    reset = 0;
    #2;
    $display("%4t |   %b   |   %2d   |  %2d   | Switched to Mod-10", $time, reset, modulo, count);
        
        // Count till 9
    repeat(9) begin
      @(posedge clk);
      #2;
    end
    $display("%4t |   %b   |   %2d   |  %2d   | At maximum (9)", $time, reset, modulo, count);
        
        // After 9 clocks, should be at 9
    test_count = test_count + 1;
    if (count !== 4'd9) begin
      $display("ERROR: Mod-10 counter should be at 9, got %d", count);
      fail_count = fail_count + 1;
    end else begin
      pass_count = pass_count + 1;
    end
        
        // next clock should wrap to 0
    @(posedge clk);
    #2;
    $display("%4t |   %b   |   %2d   |  %2d   | Wrapped to 0", $time, reset, modulo, count);
    test_count = test_count + 1;
    if (count !== 4'd0) begin
      $display("ERROR: Mod-10 counter should wrap to 0, got %d", count);
      fail_count = fail_count + 1;
    end else begin
      pass_count = pass_count + 1;
    end
        
        // Test Mod-16 Counter (or modulo=0 treated as 16)
    modulo <= 4'd0;
    $display("\n--- Testing Mod-16 Counter (modulo=0) ---");
        
    reset = 1;
    #2;
    reset = 0;
    #2;
    $display("%4t |   %b   |   %2d   |  %2d   | Switched to Mod-16", $time, reset, modulo, count);
    
        // Count to 15
    repeat(15) begin
      @(posedge clk);
      #2;
    end
    $display("%4t |   %b   |   %2d   |  %2d   | At maximum (15)", $time, reset, modulo, count);
    
      	// should be 15
    test_count = test_count + 1;
    if (count !== 4'd15) begin
      $display("ERROR: Mod-16 counter should be at 15, got %d", count);
      fail_count = fail_count + 1;
    end else begin
      pass_count = pass_count + 1;
    end
        
        // next clock should wrap to 0
    @(posedge clk);
    #2;
    $display("%4t |   %b   |   %2d   |  %2d   | Wrapped to 0", $time, reset, modulo, count);
        
    test_count = test_count + 1;
    if (count !== 4'd0) begin
      $display("ERROR: Mod-16 counter should wrap to 0, got %d", count);
      fail_count = fail_count + 1;
    end else begin
      pass_count = pass_count + 1;
    end
        
        // Test changing modulo during operation
    $display("\n--- Testing Modulo Change During Operation ---");
      
    modulo <= 4'd7;
      
    reset = 1;
    #2;
    reset = 0;
    #2;
        
        // Count to 3
    repeat(3) begin
      @(posedge clk);
      #2;
    end
    $display("%4t |   %b   |   %2d   |  %2d   | At count 3 with Mod-7", $time, reset, modulo, count);
    
        // Change to Mod-3 (should wrap on next clock since 3 >= 3)
    modulo <= 4'd3;
    @(posedge clk);
    #2;
    $display("%4t |   %b   |   %2d   |  %2d   | Changed to Mod-3", $time, reset, modulo, count);
        
        // Since count was 3 and modulo is now 3, it should wrap to 0
    test_count = test_count + 1;
    if (count !== 4'd0) begin
      $display("ERROR: Should wrap to 0 when count >= modulo, got %d", count);
      fail_count = fail_count + 1;
    end else begin
      pass_count = pass_count + 1;
    end
        
        // Test asynchronous reset during counting
    $display("\n--- Testing Asynchronous Reset ---");
    modulo <= 4'd8;
    reset = 1;
    #2;
    reset = 0;
    #2;
        
    repeat(5) begin
      @(posedge clk);
      #2;
    end
        
    $display("%4t |   %b   |   %2d   |  %2d   | Before reset", $time, reset, modulo, count);
        
        // Assert reset mid-cycle
    #3;
    reset = 1;
    #1;
    $display("%4t |   %b   |   %2d   |  %2d   | Async reset (mid-cycle)", $time, reset, modulo, count);
        
    test_count = test_count + 1;
    if (count !== 4'd0) begin
      $display("ERROR: Asynchronous reset failed, count=%d", count);
      fail_count = fail_count + 1;
    end else begin
      pass_count = pass_count + 1;
    end
        
    reset = 0;
    #10;
        
        // Display final summary
    $display("\n============================================================");
    $display("Test Summary:");
    $display("Total Tests: %0d", test_count);
    $display("Passed : %0.2f%%", (pass_count * 100)/test_count);
    $display("Failed : %0.2f%%", (fail_count * 100)/test_count);
    if (fail_count == 0)
      $display("\n*** ALL TESTS PASSED ***");
    else
      $display("\n*** SOME TESTS FAILED ***");
    $display("============================================================");
        
    $display("\nTest completed");
      
    #10;
    $finish();
  end

endmodule

post_11/dump.vcd
$date
Wed Jun  3 03:02:56 2026
$end
$version
Riviera-PRO Version 2025.04.139.9738
$end
$timescale
1 ps
$end

$scope module tb_top $end
$var wire 4 ! count [3:0] $end
$var reg 1 " clk $end
$var reg 1 # reset $end
$var reg 4 $ modulo [3:0] $end
$var integer 32 % test_count $end
$var integer 32 & pass_count $end
$var integer 32 ' fail_count $end

$scope module dut $end
$var wire 1 ( reset $end
$var wire 1 ) clk $end
$var wire 4 * modulo [3:0] $end
$var reg 4 + count [3:0] $end
$upscope $end

$upscope $end

$enddefinitions $end
$dumpvars
b0 !
0"
1#
b101 $
b0 %
b0 &
b0 '
1(
0)
b101 *
b0 +
$end
#5000
1"
1)
#10000
0"
0)
#12000
b1 %
b1 &
0#
0(
#15000
1"
1)
b1 +
b1 !
#20000
0"
0)
#25000
1"
1)
b10 +
b10 !
#30000
0"
0)
#35000
1"
1)
b11 +
b11 !
#40000
0"
0)
#45000
1"
1)
b100 +
b100 !
#50000
0"
0)
#55000
1"
1)
b0 +
b0 !
#57000
b10 %
b10 &
1#
1(
b11 $
b11 *
#59000
0#
0(
#60000
0"
0)
#65000
1"
1)
b1 +
b1 !
#70000
0"
0)
#75000
1"
1)
b10 +
b10 !
#80000
0"
0)
#85000
1"
1)
b0 +
b0 !
#87000
b11 %
b11 &
1#
1(
b1010 $
b1010 *
#89000
0#
0(
#90000
0"
0)
#95000
1"
1)
b1 +
b1 !
#100000
0"
0)
#105000
1"
1)
b10 +
b10 !
#110000
0"
0)
#115000
1"
1)
b11 +
b11 !
#120000
0"
0)
#125000
1"
1)
b100 +
b100 !
#130000
0"
0)
#135000
1"
1)
b101 +
b101 !
#140000
0"
0)
#145000
1"
1)
b110 +
b110 !
#150000
0"
0)
#155000
1"
1)
b111 +
b111 !
#160000
0"
0)
#165000
1"
1)
b1000 +
b1000 !
#170000
0"
0)
#175000
1"
1)
b1001 +
b1001 !
#177000
b100 %
b100 &
#180000
0"
0)
#185000
1"
1)
b0 +
b0 !
#187000
b101 %
b101 &
1#
1(
b0 $
b0 *
#189000
0#
0(
#190000
0"
0)
#195000
1"
1)
b1 +
b1 !
#200000
0"
0)
#205000
1"
1)
b10 +
b10 !
#210000
0"
0)
#215000
1"
1)
b11 +
b11 !
#220000
0"
0)
#225000
1"
1)
b100 +
b100 !
#230000
0"
0)
#235000
1"
1)
b101 +
b101 !
#240000
0"
0)
#245000
1"
1)
b110 +
b110 !
#250000
0"
0)
#255000
1"
1)
b111 +
b111 !
#260000
0"
0)
#265000
1"
1)
b1000 +
b1000 !
#270000
0"
0)
#275000
1"
1)
b1001 +
b1001 !
#280000
0"
0)
#285000
1"
1)
b1010 +
b1010 !
#290000
0"
0)
#295000
1"
1)
b1011 +
b1011 !
#300000
0"
0)
#305000
1"
1)
b1100 +
b1100 !
#310000
0"
0)
#315000
1"
1)
b1101 +
b1101 !
#320000
0"
0)
#325000
1"
1)
b1110 +
b1110 !
#330000
0"
0)
#335000
1"
1)
b1111 +
b1111 !
#337000
b110 %
b110 &
#340000
0"
0)
#345000
1"
1)
b0 +
b0 !
#347000
b111 %
b111 &
1#
1(
b111 $
b111 *
#349000
0#
0(
#350000
0"
0)
#355000
1"
1)
b1 +
b1 !
#360000
0"
0)
#365000
1"
1)
b10 +
b10 !
#370000
0"
0)
#375000
1"
1)
b11 +
b11 !
#377000
b11 $
b11 *
#380000
0"
0)
#385000
1"
1)
b0 +
b0 !
#387000
b1000 %
b1000 &
1#
1(
b1000 $
b1000 *
#389000
0#
0(
#390000
0"
0)
#395000
1"
1)
b1 +
b1 !
#400000
0"
0)
#405000
1"
1)
b10 +
b10 !
#410000
0"
0)
#415000
1"
1)
b11 +
b11 !
#420000
0"
0)
#425000
1"
1)
b100 +
b100 !
#430000
0"
0)
#435000
1"
1)
b101 +
b101 !
#440000
0"
1#
1(
0)
b0 +
b0 !
#441000
b1001 %
b1001 &
0#
0(
#445000
1"
1)
b1 +
b1 !
#450000
0"
0)
#455000
1"
1)
b10 +
b10 !
