post_10/design.sv
`timescale 1ns/1ps

module updown_counter (input clk, reset, up_down, output reg [3:0] count);

    always @(posedge clk, posedge reset) begin
      if (reset) count <= 4'b0000;
        else if (! reset) begin
          if (up_down) count <= count + 4'b0001;
            else count <= count - 4'b0001;
        end
        else count <= count;
    end
endmodule

post_10/testbench.sv
`timescale 1ns/1ps

module updown_counter_tb ();
  reg clk_i, reset_i, up_down_i;
  wire [3:0] out;
  
  updown_counter Call0 (.clk(clk_i), .reset(reset_i), .up_down(up_down_i), .count(out));
  
  // clock behaviour
  initial begin 
    clk_i = 1'b1;
    forever
    #0.5 clk_i = ~clk_i; //clk with Tp of 1ns
  end
  
  //Tasks for testing
  task tst_upcnt();
    reg [3:0] exp_up;
  	begin
      //preset values
      up_down_i = 1'b1;
      
      //reset code
      reset_i = 1'b1;
      @(posedge clk_i);
      reset_i = 1'b0;
      @(posedge clk_i);
      
      //UP COUNT task code
      $display("ENTERED UP COUNT TASK");
      reset_i = 1'b0;
      exp_up = 0;
      repeat (16) 
        begin
          if (out == exp_up)
            $display("time: %t | out: %d | expected: %d", $time, out, exp_up);
          else
            $error("ISSUE IN UP COUNTING");
          
          exp_up += 1;
          @(posedge clk_i);
        end
        
      @(posedge clk_i);
      $display("[PASS if no Error(s) in LOG ] UPCOUNT TASK EXITED");
  	end
  endtask
  
  task tst_downcnt();
    reg [3:0] exp_down;
  	begin
      //preset values
      up_down_i = 1'b0;
      
      //reset code
      reset_i = 1'b1;
      @(posedge clk_i);
      reset_i = 1'b0;
      @(posedge clk_i);
      
      // DOWN COUNT task code
      $display("ENTERED DOWN COUNT TASK");
      reset_i = 1'b0;
      exp_down = 0;
      repeat (16)
        begin
          #0.01;
          exp_down -= 1;
          if (out == exp_down)
            $display("time: %t | out: %d | expected: %d", $time, out, exp_down);
          else
            $error("ISSUE IN DOWN COUNTING");
          
          @(posedge clk_i);
        end
      
      @(posedge clk_i);
      $display("[PASS if no Error(s) in LOG ] DOWNCOUNT TASK EXITED");
    end
  endtask
  
  // Test Flow
  initial begin
    $dumpfile("dump.vcd");
    $dumpvars(0, updown_counter_tb);
    
    @(posedge clk_i);
    tst_upcnt();
    tst_downcnt();
    
    #5 $finish();
  end
endmodule

post_10/dump.vcd
$date
Sun May 24 12:15:50 2026
$end
$version
Riviera-PRO Version 2025.04.139.9738
$end
$timescale
1 ps
$end

$scope module updown_counter_tb $end
$var wire 4 ! out [3:0] $end
$var reg 1 " clk_i $end
$var reg 1 # reset_i $end
$var reg 1 $ up_down_i $end

$scope module Call0 $end
$var wire 1 % clk $end
$var wire 1 & reset $end
$var wire 1 ' up_down $end
$var reg 4 ( count [3:0] $end
$upscope $end


$scope task tst_upcnt $end
$var reg 4 ) exp_up [3:0] $end
$upscope $end


$scope task tst_downcnt $end
$var reg 4 * exp_down [3:0] $end
$upscope $end

$upscope $end

$enddefinitions $end
$dumpvars
bx !
1"
x#
x$
1%
x&
x'
bx (
bx )
bx *
$end
#500
0"
0%
#1000
1"
1%
1$
1#
1&
1'
b0 (
b0 !
#1500
0"
0%
#2000
1"
1%
0#
0&
#2500
0"
0%
#3000
1"
1%
b1 )
b1 (
b1 !
#3500
0"
0%
#4000
1"
1%
b10 )
b10 (
b10 !
#4500
0"
0%
#5000
1"
1%
b11 )
b11 (
b11 !
#5500
0"
0%
#6000
1"
1%
b100 )
b100 (
b100 !
#6500
0"
0%
#7000
1"
1%
b101 )
b101 (
b101 !
#7500
0"
0%
#8000
1"
1%
b110 )
b110 (
b110 !
#8500
0"
0%
#9000
1"
1%
b111 )
b111 (
b111 !
#9500
0"
0%
#10000
1"
1%
b1000 )
b1000 (
b1000 !
#10500
0"
0%
#11000
1"
1%
b1001 )
b1001 (
b1001 !
#11500
0"
0%
#12000
1"
1%
b1010 )
b1010 (
b1010 !
#12500
0"
0%
#13000
1"
1%
b1011 )
b1011 (
b1011 !
#13500
0"
0%
#14000
1"
1%
b1100 )
b1100 (
b1100 !
#14500
0"
0%
#15000
1"
1%
b1101 )
b1101 (
b1101 !
#15500
0"
0%
#16000
1"
1%
b1110 )
b1110 (
b1110 !
#16500
0"
0%
#17000
1"
1%
b1111 )
b1111 (
b1111 !
#17500
0"
0%
#18000
1"
1%
b0 )
b0 (
b0 !
#18500
0"
0%
#19000
1"
1%
b1 (
b1 !
#19500
0"
0%
#20000
1"
1%
0$
1#
1&
0'
b0 (
b0 !
#20500
0"
0%
#21000
1"
1%
0#
0&
#21500
0"
0%
#22000
1"
1%
b0 *
b1111 (
b1111 !
#22010
b1111 *
#22500
0"
0%
#23000
1"
1%
b1110 (
b1110 !
#23010
b1110 *
#23500
0"
0%
#24000
1"
1%
b1101 (
b1101 !
#24010
b1101 *
#24500
0"
0%
#25000
1"
1%
b1100 (
b1100 !
#25010
b1100 *
#25500
0"
0%
#26000
1"
1%
b1011 (
b1011 !
#26010
b1011 *
#26500
0"
0%
#27000
1"
1%
b1010 (
b1010 !
#27010
b1010 *
#27500
0"
0%
#28000
1"
1%
b1001 (
b1001 !
#28010
b1001 *
#28500
0"
0%
#29000
1"
1%
b1000 (
b1000 !
#29010
b1000 *
#29500
0"
0%
#30000
1"
1%
b111 (
b111 !
#30010
b111 *
#30500
0"
0%
#31000
1"
1%
b110 (
b110 !
#31010
b110 *
#31500
0"
0%
#32000
1"
1%
b101 (
b101 !
#32010
b101 *
#32500
0"
0%
#33000
1"
1%
b100 (
b100 !
#33010
b100 *
#33500
0"
0%
#34000
1"
1%
b11 (
b11 !
#34010
b11 *
#34500
0"
0%
#35000
1"
1%
b10 (
b10 !
#35010
b10 *
#35500
0"
0%
#36000
1"
1%
b1 (
b1 !
#36010
b1 *
#36500
0"
0%
#37000
1"
1%
b0 (
b0 !
#37010
b0 *
#37500
0"
0%
#38000
1"
1%
b1111 (
b1111 !
#38500
0"
0%
#39000
1"
1%
b1110 (
b1110 !
#39500
0"
0%
#40000
1"
1%
b1101 (
b1101 !
#40500
0"
0%
#41000
1"
1%
b1100 (
b1100 !
#41500
0"
0%
#42000
1"
1%
b1011 (
b1011 !
#42500
0"
0%
#43000
1"
1%
b1010 (
b1010 !
